tablear/ARTable.py
tablear/UserSetup.py
tablear/__init__.py
tablear/__main__.py
tablear/ui/base.png
tablear/ui/base_mask.png
tablear/ui/base_names.txt
tablear/ui/piano.png
tablear/ui/piano_mask.png
tablear-1.1.4.dist-info/LICENSE
tablear-1.1.4.dist-info/METADATA
tablear-1.1.4.dist-info/WHEEL
tablear-1.1.4.dist-info/top_level.txt
tablear-1.1.4.dist-info/RECORD
