Metadata-Version: 2.1
Name: tablear
Version: 1.1.4
Summary: Print a UI and detect it with camera
Home-page: https://github.com/Sanjay-Ganeshan/TableAR
Author: Julie Ganeshan
Author-email: HeavenlyQueen@outlook.com
License: UNKNOWN
Platform: UNKNOWN
Classifier: Programming Language :: Python :: 3
Classifier: License :: OSI Approved :: GNU General Public License v3 (GPLv3)
Requires-Python: >=3.7
Requires-Dist: opencv-python (>=4.2.0.34)
Requires-Dist: numpy (>=1.18.4)
